AG/Binary.py
AG/DirUtil.py
AG/Excel.py
AG/FileUtil.py
AG/INI.py
AG/IOUtil.py
AG/LangBase.py
AG/Logger.py
AG/PathUtil.py
AG/Proto.py
AG/Singleton.py
AG/Template.py
AG/__init__.py
AGKit-1.2.5.data/data/requirements.txt
AGKit-1.2.5.dist-info/METADATA
AGKit-1.2.5.dist-info/WHEEL
AGKit-1.2.5.dist-info/top_level.txt
AGKit-1.2.5.dist-info/RECORD
